[
 {
   "id": "",
   "lesson": 1,
   "thai": "dee maag",
   "english": "very good"
 },
 {
   "id": "",
   "lesson": 1,
   "thai": "kop kun k.",
   "english": "thank you"
 },
 {
   "id": "",
   "lesson": 1,
   "thai": "koh tod",
   "english": "i am sorry"
 },
 {
   "id": "",
   "lesson": 1,
   "thai": "koh tod jing jing",
   "english": "i am very sorry"
 },
 {
   "id": "",
   "lesson": 1,
   "thai": "mai bpen rai",
   "english": "its ok, doesn’t matter"
 },
 {
   "id": "",
   "lesson": 1,
   "thai": "mai aao",
   "english": "i dont want to take"
 },
 {
   "id": "",
   "lesson": 1,
   "thai": "mai k. kap kun k.",
   "english": "no thank you"
 },
 {
   "id": "",
   "lesson": 2,
   "thai": "kop kun maag maag k.",
   "english": "thank you very much"
 },
 {
   "id": "",
   "lesson": 2,
   "thai": "kop kun maag maag k.",
   "english": "thank you very very much"
 },
 {
   "id": "",
   "lesson": 1,
   "thai": "yin dee",
   "english": "your welcome"
 },
 {
   "id": "",
   "lesson": 2,
   "thai": "yin dee tii dai ruu jag",
   "english": "nice to meet you"
 },
 {
   "id": "",
   "lesson": 2,
   "thai": "mai sabai nid noi k.",
   "english": "I am sick a little bit"
 },
 {
   "id": "",
   "lesson": 1,
   "thai": "pom/chan cheu _",
   "english": "my name is _"
 },
 {
   "id": "",
   "lesson": 2,
   "thai": "kon cheu arai?",
   "english": "what is your name?"
 },
 {
   "id": "",
   "lesson": 2,
   "thai": "Pom puud pasa thai dai nid noi",
   "english": "i speak thai a little bit"
 },
 {
   "id": "",
   "lesson": 3,
   "thai": "mai dai tam",
   "english": "i did not do it"
 },
 {
   "id": "",
   "lesson": 3,
   "thai": "mai dai puud",
   "english": "i did not say it"
 },
 {
   "id": "",
   "lesson": 3,
   "thai": "tam mai dai ",
   "english": "i can not do"
 },
 {
   "id": "",
   "lesson": 3,
   "thai": "bpai bpai",
   "english": "go away"
 },
 {
   "id": "",
   "lesson": 3,
   "thai": "maa nii noi",
   "english": "come here please"
 },
 {
   "id": "",
   "lesson": 3,
   "thai": "bpai bpai maa maa",
   "english": "come and go, on and off"
 },
 {
   "id": "",
   "lesson": 3,
   "thai": "tam gafae",
   "english": "make coffee"
 },
 {
   "id": "",
   "lesson": 3,
   "thai": "bpai wai nam tii haad salad ",
   "english": "go to swim at haad salad"
 },
 {
   "id": "",
   "lesson": 3,
   "thai": "pom rian pasa thai tii KPG",
   "english": "i study speaking thai in KPG"
 },
 {
   "id": "",
   "lesson": 3,
   "thai": "Sabai dii mai?",
   "english": "How are you?"
 },
 {
   "id": "",
   "lesson": 3,
   "thai": "Sabai dii",
   "english": "I am good"
 },
 {
   "id": "",
   "lesson": 3,
   "thai": "mai dii",
   "english": "not a good day"
 },
 {
   "id": "",
   "lesson": 3,
   "thai": "mai sabai",
   "english": "not feel good"
 },
 {
   "id": "",
   "lesson": 3,
   "thai": "mii _ mai ?",
   "english": "do you have _ ?"
 },
 {
   "id": "",
   "lesson": 4,
   "thai": "mai aao tung",
   "english": "i dont want a plastic bag"
 },
 {
   "id": "",
   "lesson": 4,
   "thai": "mai dai tam",
   "english": "I did not do it"
 },
 {
   "id": "",
   "lesson": 4,
   "thai": "puud chaa chaa noi",
   "english": "Speak a little bit slower"
 },
 {
   "id": "",
   "lesson": 2,
   "thai": "gii baht?",
   "english": "How much baht?"
 },
 {
   "id": "",
   "lesson": 3,
   "thai": "bpai glab",
   "english": "go and come back (round trip)"
 },
 {
   "id": "",
   "lesson": 4,
   "thai": "Gii mong laew?",
   "english": "What time is it?"
 },
 {
   "id": "",
   "lesson": 4,
   "thai": "Mii wela",
   "english": "Have time"
 },
 {
   "id": "",
   "lesson": 4,
   "thai": "aao iig mai?",
   "english": "Do you want more?"
 },
 {
   "id": "",
   "lesson": 4,
   "thai": "Tam arai yuu?",
   "english": "What are you doing?"
 },
 {
   "id": "",
   "lesson": 4,
   "thai": "Gin arai yuu?",
   "english": "What are you eating?"
 },
 {
   "id": "",
   "lesson": 4,
   "thai": "Pom rag kun",
   "english": "I love you"
 },
 {
   "id": "",
   "lesson": 4,
   "thai": "Arai sod?",
   "english": "What is fresh?"
 }
]
